COPYING
README.rst
setup.py
ioctl_opt/__init__.py
ioctl_opt.egg-info/PKG-INFO
ioctl_opt.egg-info/SOURCES.txt
ioctl_opt.egg-info/dependency_links.txt
ioctl_opt.egg-info/top_level.txt