Metadata-Version: 2.1
Name: ioctl-opt
Version: 1.3
Summary: Functions to compute fnctl.ioctl's opt argument
Home-page: http://github.com/vpelletier/python-ioctl-opt
Author: Vincent Pelletier
Author-email: plr.vincent@gmail.com
License: GPL 2+
Keywords: ioctl
Classifier: Intended Audience :: Information Technology
Classifier: License :: OSI Approved :: GNU General Public License (GPL)
Classifier: Operating System :: POSIX :: Linux
Classifier: Programming Language :: Python :: 2.7
Classifier: Programming Language :: Python :: 3
License-File: COPYING
